ethutil/__init__.py
ethutil/eth.py
ethutil-0.0.6.dist-info/LICENSE
ethutil-0.0.6.dist-info/METADATA
ethutil-0.0.6.dist-info/WHEEL
ethutil-0.0.6.dist-info/top_level.txt
ethutil-0.0.6.dist-info/RECORD
