Metadata-Version: 2.1
Name: ethutil
Version: 0.0.6
Summary: eth utils
Home-page: https://github.com/362228416/ethutils-py
Author: CS
Author-email: 362228416@qq.com
License: UNKNOWN
Platform: UNKNOWN
Classifier: Programming Language :: Python :: 3
Classifier: License :: OSI Approved :: MIT License
Classifier: Operating System :: OS Independent
Requires-Python: >=3.6
